nlsq/__init__.py
nlsq/_version.py
nlsq/callbacks.py
nlsq/common_jax.py
nlsq/common_scipy.py
nlsq/config.py
nlsq/constants.py
nlsq/device.py
nlsq/py.typed
nlsq/types.py
nlsq/caching/__init__.py
nlsq/caching/compilation_cache.py
nlsq/caching/core.py
nlsq/caching/memory_manager.py
nlsq/caching/memory_pool.py
nlsq/caching/smart_cache.py
nlsq/caching/unified_cache.py
nlsq/cli/__init__.py
nlsq/cli/data_loaders.py
nlsq/cli/errors.py
nlsq/cli/main.py
nlsq/cli/model_registry.py
nlsq/cli/model_validation.py
nlsq/cli/result_exporter.py
nlsq/cli/visualization.py
nlsq/cli/workflow_runner.py
nlsq/cli/commands/__init__.py
nlsq/cli/commands/batch.py
nlsq/cli/commands/config.py
nlsq/cli/commands/fit.py
nlsq/cli/commands/info.py
nlsq/cli/templates/__init__.py
nlsq/cli/templates/custom_model_template.py
nlsq/cli/templates/workflow_config_template.yaml
nlsq/core/__init__.py
nlsq/core/factories.py
nlsq/core/feature_flags.py
nlsq/core/functions.py
nlsq/core/least_squares.py
nlsq/core/loss_functions.py
nlsq/core/minpack.py
nlsq/core/optimizer_base.py
nlsq/core/profiler.py
nlsq/core/sparse_jacobian.py
nlsq/core/trf.py
nlsq/core/trf_jit.py
nlsq/core/workflow.py
nlsq/core/adapters/__init__.py
nlsq/core/adapters/curve_fit_adapter.py
nlsq/core/orchestration/__init__.py
nlsq/core/orchestration/covariance_computer.py
nlsq/core/orchestration/data_preprocessor.py
nlsq/core/orchestration/entities.py
nlsq/core/orchestration/optimization_selector.py
nlsq/core/orchestration/streaming_coordinator.py
nlsq/diagnostics/__init__.py
nlsq/diagnostics/gradient_health.py
nlsq/diagnostics/health_report.py
nlsq/diagnostics/identifiability.py
nlsq/diagnostics/parameter_sensitivity.py
nlsq/diagnostics/plugin.py
nlsq/diagnostics/recommendations.py
nlsq/diagnostics/types.py
nlsq/facades/__init__.py
nlsq/facades/diagnostics_facade.py
nlsq/facades/optimization_facade.py
nlsq/facades/stability_facade.py
nlsq/global_optimization/__init__.py
nlsq/global_optimization/bipop.py
nlsq/global_optimization/bounds_transform.py
nlsq-0.6.4.dist-info/licenses/AUTHORS.md
nlsq-0.6.4.dist-info/licenses/LICENSE
nlsq-0.6.4.dist-info/METADATA
nlsq-0.6.4.dist-info/WHEEL
nlsq-0.6.4.dist-info/entry_points.txt
nlsq-0.6.4.dist-info/top_level.txt
nlsq-0.6.4.dist-info/RECORD
