Metadata-Version: 2.4
Name: nlsq
Version: 0.6.4
Summary: GPU/TPU accelerated nonlinear least-squares curve fitting using JAX
Author: Lucas Hofer (Original JAXFit), Milan Krstajić (Original JAXFit), Robert P. Smith (Original JAXFit)
Author-email: Wei Chen <wchen@anl.gov>
Maintainer-email: Wei Chen <wchen@anl.gov>
License-Expression: MIT
Project-URL: Homepage, https://github.com/imewei/NLSQ
Project-URL: Documentation, https://nlsq.readthedocs.io
Project-URL: Repository, https://github.com/imewei/NLSQ.git
Project-URL: Issues, https://github.com/imewei/NLSQ/issues
Project-URL: Changelog, https://github.com/imewei/NLSQ/blob/main/CHANGELOG.md
Keywords: curve-fitting,optimization,least-squares,jax,gpu,tpu,scientific-computing,machine-learning
Classifier: Development Status :: 4 - Beta
Classifier: Intended Audience :: Science/Research
Classifier: Operating System :: OS Independent
Classifier: Programming Language :: Python :: 3
Classifier: Programming Language :: Python :: 3.12
Classifier: Programming Language :: Python :: 3.13
Classifier: Programming Language :: Python :: 3 :: Only
Classifier: Topic :: Scientific/Engineering :: Mathematics
Classifier: Topic :: Scientific/Engineering :: Physics
Classifier: Topic :: Scientific/Engineering :: Artificial Intelligence
Classifier: Typing :: Typed
Requires-Python: >=3.12
License-File: LICENSE
License-File: AUTHORS.md
Requires-Dist: numpy>=2.2
Requires-Dist: scipy>=1.16.0
Requires-Dist: jax>=0.8.0
Requires-Dist: jaxlib>=0.8.0
Requires-Dist: optax>=0.2.6
Requires-Dist: matplotlib>=3.10.0
Requires-Dist: psutil>=7.0.0
Requires-Dist: tqdm>=4.67.0
Requires-Dist: h5py>=3.15.0
Provides-Extra: dev
Requires-Dist: pytest>=9.0.0; extra == "dev"
Requires-Dist: pytest-cov>=7.0.0; extra == "dev"
Requires-Dist: pytest-xdist>=3.8.0; extra == "dev"
Requires-Dist: pytest-rerunfailures>=16.0; extra == "dev"
Requires-Dist: black>=25.0.0; extra == "dev"
Requires-Dist: ruff>=0.14.0; extra == "dev"
Requires-Dist: mypy>=1.19.0; extra == "dev"
Requires-Dist: pre-commit>=4.5.0; extra == "dev"
Requires-Dist: ipython>=9.0.0; extra == "dev"
Requires-Dist: bandit>=1.9.0; extra == "dev"
Requires-Dist: pyupgrade>=3.21.0; extra == "dev"
Provides-Extra: docs
Requires-Dist: sphinx>=8.0.0; extra == "docs"
Requires-Dist: furo>=2025.0.0; extra == "docs"
Requires-Dist: sphinx-copybutton>=0.5.2; extra == "docs"
Requires-Dist: sphinx-autodoc-typehints>=3.5.0; extra == "docs"
Requires-Dist: sphinx-design>=0.6.0; extra == "docs"
Requires-Dist: ipython>=9.0.0; extra == "docs"
Requires-Dist: myst-parser>=4.0.0; extra == "docs"
Provides-Extra: test
Requires-Dist: pytest>=9.0.0; extra == "test"
Requires-Dist: pytest-cov>=7.0.0; extra == "test"
Requires-Dist: pytest-xdist>=3.8.0; extra == "test"
Requires-Dist: pytest-timeout>=2.4.0; extra == "test"
Requires-Dist: pytest-rerunfailures>=16.0; extra == "test"
Requires-Dist: hypothesis>=6.148.0; extra == "test"
Provides-Extra: benchmark
Requires-Dist: pytest-benchmark>=5.2.3; extra == "benchmark"
Requires-Dist: asv>=0.6.5; extra == "benchmark"
Requires-Dist: memory-profiler>=0.61.0; extra == "benchmark"
Requires-Dist: psutil>=7.2.0; extra == "benchmark"
Provides-Extra: performance
Requires-Dist: xxhash>=3.6.0; extra == "performance"
Provides-Extra: yaml
Requires-Dist: pyyaml>=6.0.3; extra == "yaml"
Provides-Extra: jupyter
Requires-Dist: jupyterlab>=4.5.0; extra == "jupyter"
Requires-Dist: ipykernel>=7.0.0; extra == "jupyter"
Requires-Dist: notebook>=7.5.0; extra == "jupyter"
Provides-Extra: build
Requires-Dist: build>=1.3.0; extra == "build"
Requires-Dist: twine>=6.2.0; extra == "build"
Requires-Dist: setuptools>=80.0.0; extra == "build"
Requires-Dist: setuptools-scm>=9.2.0; extra == "build"
Requires-Dist: wheel>=0.45.0; extra == "build"
Provides-Extra: gui-qt
Requires-Dist: PySide6>=6.10.0; extra == "gui-qt"
Requires-Dist: pyqtgraph>=0.14.0; extra == "gui-qt"
Requires-Dist: pyyaml>=6.0.3; extra == "gui-qt"
Requires-Dist: pytest-qt>=4.5.0; extra == "gui-qt"
Provides-Extra: global
Requires-Dist: evosax<0.3.0,>=0.2.0; extra == "global"
Provides-Extra: all
Requires-Dist: pytest>=9.0.0; extra == "all"
Requires-Dist: pytest-cov>=7.0.0; extra == "all"
Requires-Dist: pytest-xdist>=3.8.0; extra == "all"
Requires-Dist: pytest-rerunfailures>=16.0; extra == "all"
Requires-Dist: black>=25.0.0; extra == "all"
Requires-Dist: ruff>=0.14.0; extra == "all"
Requires-Dist: mypy>=1.19.0; extra == "all"
Requires-Dist: pre-commit>=4.5.0; extra == "all"
Requires-Dist: ipython>=9.0.0; extra == "all"
Requires-Dist: bandit>=1.9.0; extra == "all"
Requires-Dist: pyupgrade>=3.21.0; extra == "all"
Requires-Dist: sphinx>=8.0.0; extra == "all"
Requires-Dist: furo>=2025.0.0; extra == "all"
Requires-Dist: sphinx-copybutton>=0.5.2; extra == "all"
Requires-Dist: sphinx-autodoc-typehints>=3.5.0; extra == "all"
Requires-Dist: sphinx-design>=0.6.0; extra == "all"
Requires-Dist: myst-parser>=4.0.0; extra == "all"
Requires-Dist: hypothesis>=6.148.0; extra == "all"
Requires-Dist: pytest-timeout>=2.4.0; extra == "all"
Requires-Dist: pytest-benchmark>=5.2.3; extra == "all"
Requires-Dist: asv>=0.6.5; extra == "all"
Requires-Dist: memory-profiler>=0.61.0; extra == "all"
Requires-Dist: psutil>=7.2.0; extra == "all"
Requires-Dist: xxhash>=3.6.0; extra == "all"
Requires-Dist: pyyaml>=6.0.3; extra == "all"
Requires-Dist: jupyterlab>=4.5.0; extra == "all"
Requires-Dist: ipykernel>=7.0.0; extra == "all"
Requires-Dist: notebook>=7.5.0; extra == "all"
Requires-Dist: build>=1.3.0; extra == "all"
Requires-Dist: twine>=6.2.0; extra == "all"
Requires-Dist: setuptools>=80.0.0; extra == "all"
Requires-Dist: setuptools-scm>=9.2.0; extra == "all"
Requires-Dist: wheel>=0.45.0; extra == "all"
Requires-Dist: PySide6>=6.10.0; extra == "all"
Requires-Dist: pyqtgraph>=0.14.0; extra == "all"
Requires-Dist: pytest-qt>=4.5.0; extra == "all"
Requires-Dist: evosax<0.3.0,>=0.2.0; extra == "all"
Dynamic: license-file
